{"2022-03-21 04:54:38.21": [{"Altitude (m)": "9717.4", "Longitude0 (NW)(deg East)": "[120.079]", "Latitude0 (NW)(deg North)": "[47.132]", "Longitude1 (SE)(deg East)": "[119.906]", "Latitude1 (SE)(deg North)": "[47.016]", "Width of Detection Box (m East-West)": "37.1943359375", "Height of Detection Box (m North-South)": "34.547119140625"}]}{"2022-03-21 04:54:38.42": [{"Altitude (m)": "22071.72", "Longitude0 (NW)(deg East)": "[121.831]", "Latitude0 (NW)(deg North)": "[46.946]", "Longitude1 (SE)(deg East)": "[121.633]", "Latitude1 (SE)(deg North)": "[46.844]", "Width of Detection Box (m East-West)": "41.9622802734375", "Height of Detection Box (m North-South)": "31.1444091796875"}]}