{"2022-03-21 05:09:48.75": [{"Altitude (m)": "20296.69", "Longitude0 (NW)(deg East)": "[120.762]", "Latitude0 (NW)(deg North)": "[47.764]", "Longitude1 (SE)(deg East)": "[120.59]", "Latitude1 (SE)(deg North)": "[47.668]", "Width of Detection Box (m East-West)": "36.1593017578125", "Height of Detection Box (m North-South)": "28.55908203125"}]}{"2022-03-21 05:09:48.79": [{"Altitude (m)": "20777.0", "Longitude0 (NW)(deg East)": "[120.334]", "Latitude0 (NW)(deg North)": "[46.578]", "Longitude1 (SE)(deg East)": "[120.178]", "Latitude1 (SE)(deg North)": "[46.45]", "Width of Detection Box (m East-West)": "33.3970947265625", "Height of Detection Box (m North-South)": "38.16705322265625"}]}